topsis_dhruv_102303116/__init__.py
topsis_dhruv_102303116/topsis.py
topsis_dhruv_102303116-1.0.0.dist-info/licenses/LICENSE
topsis_dhruv_102303116-1.0.0.dist-info/METADATA
topsis_dhruv_102303116-1.0.0.dist-info/WHEEL
topsis_dhruv_102303116-1.0.0.dist-info/entry_points.txt
topsis_dhruv_102303116-1.0.0.dist-info/top_level.txt
topsis_dhruv_102303116-1.0.0.dist-info/RECORD
